{"userId":504,"recommendations":[{"movieId":3379,"rating":4.991644},{"movieId":1046,"rating":4.861522},{"movieId":177593,"rating":4.8516736},{"movieId":27523,"rating":4.841318},{"movieId":33649,"rating":4.817914},{"movieId":5490,"rating":4.8076224},{"movieId":132333,"rating":4.8076224},{"movieId":171495,"rating":4.806759},{"movieId":4495,"rating":4.7864275},{"movieId":6201,"rating":4.7864275}]}
{"userId":554,"recommendations":[{"movieId":3142,"rating":5.8876057},{"movieId":32892,"rating":5.869801},{"movieId":26171,"rating":5.7695527},{"movieId":45503,"rating":5.7613626},{"movieId":7121,"rating":5.754935},{"movieId":1046,"rating":5.686312},{"movieId":90888,"rating":5.685693},{"movieId":166534,"rating":5.667452},{"movieId":112804,"rating":5.6498785},{"movieId":68073,"rating":5.593483}]}
{"userId":598,"recommendations":[{"movieId":74754,"rating":6.202379},{"movieId":3993,"rating":5.697213},{"movieId":72171,"rating":5.6951504},{"movieId":102903,"rating":5.675432},{"movieId":135532,"rating":5.6113095},{"movieId":3283,"rating":5.1916013},{"movieId":91976,"rating":5.1671815},{"movieId":4102,"rating":5.0898523},{"movieId":54256,"rating":5.0039954},{"movieId":101577,"rating":4.990656}]}
