{"userId":161,"recommendations":[{"movieId":2693,"rating":5.9347615},{"movieId":89904,"rating":5.9282627},{"movieId":86320,"rating":5.6937385},{"movieId":3925,"rating":5.429479},{"movieId":3134,"rating":5.41194},{"movieId":7025,"rating":5.246351},{"movieId":4649,"rating":5.2148485},{"movieId":6184,"rating":5.214245},{"movieId":106100,"rating":5.1792984},{"movieId":945,"rating":5.1589766}]}
{"userId":555,"recommendations":[{"movieId":33649,"rating":5.641053},{"movieId":93988,"rating":5.317894},{"movieId":93008,"rating":5.2598844},{"movieId":77846,"rating":5.2598844},{"movieId":25906,"rating":5.2598844},{"movieId":3814,"rating":5.2170787},{"movieId":92494,"rating":5.1387897},{"movieId":102217,"rating":5.1387897},{"movieId":104339,"rating":5.0962},{"movieId":74282,"rating":5.0863357}]}
