{"userId":21,"recommendations":[{"movieId":67618,"rating":4.9215407},{"movieId":3086,"rating":4.7634525},{"movieId":92643,"rating":4.5319266},{"movieId":26614,"rating":4.5131054},{"movieId":3283,"rating":4.47568},{"movieId":69394,"rating":4.4293866},{"movieId":90576,"rating":4.4293866},{"movieId":41724,"rating":4.4293866},{"movieId":185029,"rating":4.404623},{"movieId":33090,"rating":4.391005}]}
{"userId":214,"recommendations":[{"movieId":5490,"rating":4.025429},{"movieId":132333,"rating":4.025429},{"movieId":232,"rating":4.016309},{"movieId":3846,"rating":4.001608},{"movieId":5915,"rating":3.9435854},{"movieId":3379,"rating":3.9216025},{"movieId":1046,"rating":3.920753},{"movieId":928,"rating":3.8161523},{"movieId":8542,"rating":3.7974758},{"movieId":1949,"rating":3.776713}]}
