{"userId":280,"recommendations":[{"movieId":74226,"rating":5.212094},{"movieId":138966,"rating":5.212094},{"movieId":184245,"rating":5.212094},{"movieId":84273,"rating":5.212094},{"movieId":134796,"rating":5.212094},{"movieId":179135,"rating":5.212094},{"movieId":26073,"rating":5.212094},{"movieId":117531,"rating":5.212094},{"movieId":7071,"rating":5.212094},{"movieId":86237,"rating":5.212094}]}
{"userId":440,"recommendations":[{"movieId":3379,"rating":5.177025},{"movieId":8477,"rating":5.047341},{"movieId":33649,"rating":5.011256},{"movieId":104339,"rating":4.9049177},{"movieId":171495,"rating":4.8425064},{"movieId":78836,"rating":4.785988},{"movieId":27523,"rating":4.7663527},{"movieId":6666,"rating":4.764559},{"movieId":30745,"rating":4.7393017},{"movieId":132333,"rating":4.7287083}]}
{"userId":13,"recommendations":[{"movieId":3379,"rating":5.447342},{"movieId":33649,"rating":5.1945953},{"movieId":27156,"rating":5.010762},{"movieId":80906,"rating":5.003854},{"movieId":59018,"rating":4.959811},{"movieId":60943,"rating":4.959811},{"movieId":3703,"rating":4.9405313},{"movieId":104339,"rating":4.9354906},{"movieId":171495,"rating":4.9163146},{"movieId":3022,"rating":4.9095087}]}
{"userId":218,"recommendations":[{"movieId":96004,"rating":4.9999433},{"movieId":3379,"rating":4.9657693},{"movieId":68945,"rating":4.787645},{"movieId":132333,"rating":4.725361},{"movieId":5490,"rating":4.725361},{"movieId":6650,"rating":4.720727},{"movieId":3503,"rating":4.6821694},{"movieId":5915,"rating":4.6214085},{"movieId":28,"rating":4.5990944},{"movieId":95182,"rating":4.598692}]}
{"userId":348,"recommendations":[{"movieId":33649,"rating":5.696415},{"movieId":3379,"rating":5.6491566},{"movieId":104339,"rating":5.6483364},{"movieId":171495,"rating":5.5603957},{"movieId":78836,"rating":5.557576},{"movieId":177593,"rating":5.540007},{"movieId":2131,"rating":5.5295444},{"movieId":26073,"rating":5.526906},{"movieId":117531,"rating":5.526906},{"movieId":7071,"rating":5.526906}]}
