{"userId":291,"recommendations":[{"movieId":67618,"rating":5.707694},{"movieId":3925,"rating":5.3236856},{"movieId":3283,"rating":5.2036605},{"movieId":33649,"rating":5.1890683},{"movieId":130518,"rating":5.1848803},{"movieId":86377,"rating":5.1533666},{"movieId":69524,"rating":5.148285},{"movieId":87234,"rating":5.139292},{"movieId":41724,"rating":5.136925},{"movieId":69394,"rating":5.136925}]}
{"userId":325,"recommendations":[{"movieId":96004,"rating":5.110473},{"movieId":3379,"rating":4.93798},{"movieId":8477,"rating":4.934407},{"movieId":6650,"rating":4.860402},{"movieId":32582,"rating":4.828261},{"movieId":7096,"rating":4.8047976},{"movieId":104339,"rating":4.8027706},{"movieId":7767,"rating":4.800327},{"movieId":2131,"rating":4.782035},{"movieId":2732,"rating":4.776914}]}
{"userId":386,"recommendations":[{"movieId":3379,"rating":4.1217384},{"movieId":8477,"rating":4.1210585},{"movieId":104339,"rating":4.0683756},{"movieId":92494,"rating":4.015604},{"movieId":102217,"rating":4.015604},{"movieId":33649,"rating":3.9928894},{"movieId":2936,"rating":3.9073644},{"movieId":7025,"rating":3.9071126},{"movieId":33779,"rating":3.8911095},{"movieId":171495,"rating":3.8650768}]}
